platon/TP_profile.py
platon/__init__.py
platon/_atmosphere_solver.py
platon/_cupy_numpy.py
platon/_get_data.py
platon/_hist.py
platon/_hydrostatic_solver.py
platon/_interpolator_3D.py
platon/_loader.py
platon/_mie_cache.py
platon/_mie_multi_x.py
platon/_output_writer.py
platon/_params.py
platon/_species_data_reader.py
platon/_tau_calculator.py
platon/abundance_getter.py
platon/backup.py
platon/combined_retriever.py
platon/constants.py
platon/custom_dynesty_result.py
platon/eclipse_depth_calculator.py
platon/errors.py
platon/fit_info.py
platon/params.py
platon/plotter.py
platon/psis.py
platon/retrieval_result.py
platon/retriever.py
platon/surface_calculator.py
platon/transit_depth_calculator.py
platon/visualizer.py
tests/__init__.py
tests/test_TP_profiles.py
tests/test_eclipse_depth_calculator.py
tests/test_eclipse_retrieval.py
tests/test_get_data.py
tests/test_mie.py
tests/test_mie_absorption.py
tests/test_params.py
tests/test_retrieve.py
tests/test_tau_calculator.py
tests/test_transit_depth_calculator.py
platon-6.3.dist-info/LICENSE
platon-6.3.dist-info/METADATA
platon-6.3.dist-info/WHEEL
platon-6.3.dist-info/top_level.txt
platon-6.3.dist-info/RECORD
