Metadata-Version: 2.1
Name: platon
Version: 6.3
Summary: A package to compute transmission spectra and retrieve atmospheric parameters from transmission spectra
Home-page: https://github.com/ideasrule/platon
Author: Michael Zhang, Yayaati Chachan
Author-email: zmzhang@caltech.edu
Classifier: Programming Language :: Python :: 3
Classifier: License :: OSI Approved :: GNU General Public License v3 (GPLv3)
Classifier: Operating System :: OS Independent
License-File: LICENSE
Requires-Dist: numpy
Requires-Dist: scipy
Requires-Dist: emcee
Requires-Dist: dynesty
Requires-Dist: corner
Requires-Dist: future
Requires-Dist: nose
Requires-Dist: setuptools
Requires-Dist: configparser
Requires-Dist: matplotlib
